JavatutorialnetworkZhongwenXilieJiaocheng/README.md
JavatutorialnetworkZhongwenXilieJiaocheng/__init__.py
JavatutorialnetworkZhongwenXilieJiaocheng/__main__.py
JavatutorialnetworkZhongwenXilieJiaocheng/file.epub
JavatutorialnetworkZhongwenXilieJiaocheng/index.html
JavatutorialnetworkZhongwenXilieJiaocheng/css/__init__.py
JavatutorialnetworkZhongwenXilieJiaocheng/css/annotations.css
JavatutorialnetworkZhongwenXilieJiaocheng/css/main.css
JavatutorialnetworkZhongwenXilieJiaocheng/css/normalize.css
JavatutorialnetworkZhongwenXilieJiaocheng/css/popup.css
JavatutorialnetworkZhongwenXilieJiaocheng/font/__init__.py
JavatutorialnetworkZhongwenXilieJiaocheng/font/fontello.eot
JavatutorialnetworkZhongwenXilieJiaocheng/font/fontello.svg
JavatutorialnetworkZhongwenXilieJiaocheng/font/fontello.ttf
JavatutorialnetworkZhongwenXilieJiaocheng/font/fontello.woff
JavatutorialnetworkZhongwenXilieJiaocheng/img/__init__.py
JavatutorialnetworkZhongwenXilieJiaocheng/img/annotator-glyph-sprite.png
JavatutorialnetworkZhongwenXilieJiaocheng/img/annotator-icon-sprite.png
JavatutorialnetworkZhongwenXilieJiaocheng/img/apple-touch-icon.png
JavatutorialnetworkZhongwenXilieJiaocheng/img/cancelfullscreen.png
JavatutorialnetworkZhongwenXilieJiaocheng/img/close.png
JavatutorialnetworkZhongwenXilieJiaocheng/img/fullscreen.png
JavatutorialnetworkZhongwenXilieJiaocheng/img/loader.gif
JavatutorialnetworkZhongwenXilieJiaocheng/img/menu-icon.png
JavatutorialnetworkZhongwenXilieJiaocheng/img/save.png
JavatutorialnetworkZhongwenXilieJiaocheng/img/saved.png
JavatutorialnetworkZhongwenXilieJiaocheng/img/settings-s.png
JavatutorialnetworkZhongwenXilieJiaocheng/img/settings.png
JavatutorialnetworkZhongwenXilieJiaocheng/img/star.png
JavatutorialnetworkZhongwenXilieJiaocheng/js/__init__.py
JavatutorialnetworkZhongwenXilieJiaocheng/js/epub.js
JavatutorialnetworkZhongwenXilieJiaocheng/js/epub.min.js
JavatutorialnetworkZhongwenXilieJiaocheng/js/epub.min.map
JavatutorialnetworkZhongwenXilieJiaocheng/js/hooks.min.js
javatutorialnetwork_zhongwen_xilie_jiaocheng-2024.3.4.0.dist-info/METADATA
javatutorialnetwork_zhongwen_xilie_jiaocheng-2024.3.4.0.dist-info/WHEEL
javatutorialnetwork_zhongwen_xilie_jiaocheng-2024.3.4.0.dist-info/entry_points.txt
javatutorialnetwork_zhongwen_xilie_jiaocheng-2024.3.4.0.dist-info/top_level.txt
javatutorialnetwork_zhongwen_xilie_jiaocheng-2024.3.4.0.dist-info/RECORD
